juneanalytics/__init__.py
juneanalytics/version.py
juneanalytics-1.0.1.dist-info/LICENSE
juneanalytics-1.0.1.dist-info/METADATA
juneanalytics-1.0.1.dist-info/WHEEL
juneanalytics-1.0.1.dist-info/top_level.txt
juneanalytics-1.0.1.dist-info/RECORD
