Metadata-Version: 2.1
Name: juneanalytics
Version: 1.0.1
Summary: Integrate June into any python application.
Home-page: https://github.com/June-Analytics/june-python
Author: June
Author-email: ferruccio@june.so
Maintainer: June
Maintainer-email: ferruccio@june.so
License: MIT License
Platform: UNKNOWN
Classifier: Development Status :: 1 - Planning
Classifier: Intended Audience :: Developers
Classifier: License :: OSI Approved :: MIT License
Classifier: Operating System :: OS Independent
Classifier: Programming Language :: Python
Classifier: Programming Language :: Python :: 2
Classifier: Programming Language :: Python :: 2.6
Classifier: Programming Language :: Python :: 2.7
Classifier: Programming Language :: Python :: 3
Classifier: Programming Language :: Python :: 3.2
Classifier: Programming Language :: Python :: 3.3
Classifier: Programming Language :: Python :: 3.4
Classifier: Programming Language :: Python :: 3.5
Classifier: Programming Language :: Python :: 3.6
Classifier: Programming Language :: Python :: 3.7
Classifier: Programming Language :: Python :: 3.8
Requires-Dist: requests (<3.0,>=2.7)
Requires-Dist: six (>=1.5)
Requires-Dist: monotonic (>=1.5)
Requires-Dist: backoff (==1.6.0)
Requires-Dist: python-dateutil (>2.1)
